{
  "last_updated": "2026-04-22T03:14:00.619551+00:00",
  "articles": [
    {
      "title": "Former Red Sox coach Brian Butterfield headlines 2026 Maine Sports Hall of Fame class",
      "url": "https://www.bangordailynews.com/2026/04/21/sports/professional-baseball/brian-butterfield-maine-sports-hall-of-fame/",
      "byline": "Larry Mahoney",
      "image": ""
    },
    {
      "title": "UMaine men\u2019s hockey adds size up front with transfer from Arizona State",
      "url": "https://www.bangordailynews.com/2026/04/21/sports/college-ice-hockey/alfano-transfer-maine-hockey/",
      "byline": "Larry Mahoney",
      "image": ""
    }
  ]
}