{
  "last_updated": "2026-05-16T03:15:43.879995+00:00",
  "articles": [
    {
      "title": "Colby softball beats Husson with walkoff homer in regional contest",
      "url": "https://www.bangordailynews.com/2026/05/15/sports/college-softball/colby-softball-beats-husson-with-walkoff-homer-in-regional-contest/",
      "byline": "Larry Mahoney",
      "image": ""
    },
    {
      "title": "Scarborough native sparks 19-hit attack as Endicott baseball routs Husson in regional opener",
      "url": "https://www.bangordailynews.com/2026/05/15/sports/college-baseball/endicott-baseball-routs-husson-in-regional-opener/",
      "byline": "Larry Mahoney",
      "image": ""
    },
    {
      "title": "Maine high school\u00a0postseason sporting events can finally be held on Sundays",
      "url": "https://www.bangordailynews.com/2026/05/15/sports/maine-high-school-postseason-sporting-events-can-now-be-held-on-sundays/",
      "byline": "Larry Mahoney",
      "image": ""
    },
    {
      "title": "UMaine to honor College World Series baseball teams before Saturday finale",
      "url": "https://www.bangordailynews.com/2026/05/15/sports/college-baseball/umaine-college-world-series-baseball-teams/",
      "byline": "Larry Mahoney",
      "image": ""
    }
  ]
}